{
  "battle_won_mean": [
    0.0,
    0.0,
    0.0,
    0.0,
    0.0,
    0.0,
    0.0,
    0.0,
    0.0,
    0.0,
    0.0,
    0.0,
    0.0,
    0.0,
    0.0,
    0.0,
    0.0,
    0.0,
    0.0,
    0.0,
    0.0
  ],
  "battle_won_mean_T": [
    10,
    10010,
    20010,
    30010,
    40010,
    50010,
    60010,
    70010,
    80010,
    90010,
    100010,
    110010,
    120010,
    130010,
    140010,
    150010,
    160010,
    170010,
    180010,
    190010,
    200010
  ],
  "ep_length_mean": [
    10.0,
    10.0,
    10.0,
    10.0,
    10.0,
    10.0,
    10.0,
    10.0,
    10.0,
    10.0,
    10.0,
    10.0,
    10.0,
    10.0,
    10.0,
    10.0,
    10.0,
    10.0,
    10.0,
    10.0,
    10.0
  ],
  "ep_length_mean_T": [
    10,
    10010,
    20010,
    30010,
    40010,
    50010,
    60010,
    70010,
    80010,
    90010,
    100010,
    110010,
    120010,
    130010,
    140010,
    150010,
    160010,
    170010,
    180010,
    190010,
    200010
  ],
  "episode": [
    1000,
    2000,
    3000,
    4000,
    5000,
    6000,
    7000,
    8000,
    9000,
    10000,
    11000,
    12000,
    13000,
    14000,
    15000,
    16000,
    17000,
    18000,
    19000,
    20000
  ],
  "episode_T": [
    10000,
    20000,
    30000,
    40000,
    50000,
    60000,
    70000,
    80000,
    90000,
    100000,
    110000,
    120000,
    130000,
    140000,
    150000,
    160000,
    170000,
    180000,
    190000,
    200000
  ],
  "epsilon": [
    1.0,
    0.81,
    0.6200000000000001,
    0.43000000000000005,
    0.2400000000000001,
    0.050000000000000155,
    0.05,
    0.05,
    0.05,
    0.05,
    0.05,
    0.05,
    0.05,
    0.05,
    0.05,
    0.05,
    0.05,
    0.05,
    0.05,
    0.05,
    0.05
  ],
  "epsilon_T": [
    10,
    10010,
    20010,
    30010,
    40010,
    50010,
    60010,
    70010,
    80010,
    90010,
    100010,
    110010,
    120010,
    130010,
    140010,
    150010,
    160010,
    170010,
    180010,
    190010,
    200010
  ],
  "grad_norm": [
    {
      "py/reduce": [
        {
          "py/function": "torch._utils._rebuild_tensor_v2"
        },
        {
          "py/tuple": [
            {
              "py/reduce": [
                {
                  "py/function": "torch.storage._load_from_bytes"
                },
                {
                  "py/tuple": [
                    {
                      "py/b64": "gAKKCmz8nEb5IGqoUBkugAJN6QMugAJ9cQAoWBAAAABwcm90b2NvbF92ZXJzaW9ucQFN6QNYDQAA\nAGxpdHRsZV9lbmRpYW5xAohYCgAAAHR5cGVfc2l6ZXNxA31xBChYBQAAAHNob3J0cQVLAlgDAAAA\naW50cQZLBFgEAAAAbG9uZ3EHSwR1dS6AAihYBwAAAHN0b3JhZ2VxAGN0b3JjaApGbG9hdFN0b3Jh\nZ2UKcQFYDgAAADk0NjAyMTAyODM1MTY4cQJYBgAAAGN1ZGE6MHEDSwFOdHEEUS6AAl1xAFgOAAAA\nOTQ2MDIxMDI4MzUxNjhxAWEuAQAAAAAAAAAEfptE\n"
                    }
                  ]
                },
                null,
                null,
                null
              ]
            },
            0,
            {
              "py/tuple": []
            },
            {
              "py/tuple": []
            },
            false,
            {
              "py/reduce": [
                {
                  "py/type": "collections.OrderedDict"
                },
                {
                  "py/tuple": []
                },
                null,
                null,
                {
                  "py/tuple": []
                }
              ]
            }
          ]
        },
        null,
        null,
        null
      ]
    },
    {
      "py/reduce": [
        {
          "py/function": "torch._utils._rebuild_tensor_v2"
        },
        {
          "py/tuple": [
            {
              "py/reduce": [
                {
                  "py/function": "torch.storage._load_from_bytes"
                },
                {
                  "py/tuple": [
                    {
                      "py/b64": "gAKKCmz8nEb5IGqoUBkugAJN6QMugAJ9cQAoWBAAAABwcm90b2NvbF92ZXJzaW9ucQFN6QNYDQAA\nAGxpdHRsZV9lbmRpYW5xAohYCgAAAHR5cGVfc2l6ZXNxA31xBChYBQAAAHNob3J0cQVLAlgDAAAA\naW50cQZLBFgEAAAAbG9uZ3EHSwR1dS6AAihYBwAAAHN0b3JhZ2VxAGN0b3JjaApGbG9hdFN0b3Jh\nZ2UKcQFYDgAAADk0NjA1MDAzNDEyNjcycQJYBgAAAGN1ZGE6MHEDSwFOdHEEUS6AAl1xAFgOAAAA\nOTQ2MDUwMDM0MTI2NzJxAWEuAQAAAAAAAABT7bZB\n"
                    }
                  ]
                },
                null,
                null,
                null
              ]
            },
            0,
            {
              "py/tuple": []
            },
            {
              "py/tuple": []
            },
            false,
            {
              "py/reduce": [
                {
                  "py/type": "collections.OrderedDict"
                },
                {
                  "py/tuple": []
                },
                null,
                null,
                {
                  "py/tuple": []
                }
              ]
            }
          ]
        },
        null,
        null,
        null
      ]
    },
    {
      "py/reduce": [
        {
          "py/function": "torch._utils._rebuild_tensor_v2"
        },
        {
          "py/tuple": [
            {
              "py/reduce": [
                {
                  "py/function": "torch.storage._load_from_bytes"
                },
                {
                  "py/tuple": [
                    {
                      "py/b64": "gAKKCmz8nEb5IGqoUBkugAJN6QMugAJ9cQAoWBAAAABwcm90b2NvbF92ZXJzaW9ucQFN6QNYDQAA\nAGxpdHRsZV9lbmRpYW5xAohYCgAAAHR5cGVfc2l6ZXNxA31xBChYBQAAAHNob3J0cQVLAlgDAAAA\naW50cQZLBFgEAAAAbG9uZ3EHSwR1dS6AAihYBwAAAHN0b3JhZ2VxAGN0b3JjaApGbG9hdFN0b3Jh\nZ2UKcQFYDgAAADk0NjAyMTAzNDM2NzY4cQJYBgAAAGN1ZGE6MHEDSwFOdHEEUS6AAl1xAFgOAAAA\nOTQ2MDIxMDM0MzY3NjhxAWEuAQAAAAAAAACh3A5B\n"
                    }
                  ]
                },
                null,
                null,
                null
              ]
            },
            0,
            {
              "py/tuple": []
            },
            {
              "py/tuple": []
            },
            false,
            {
              "py/reduce": [
                {
                  "py/type": "collections.OrderedDict"
                },
                {
                  "py/tuple": []
                },
                null,
                null,
                {
                  "py/tuple": []
                }
              ]
            }
          ]
        },
        null,
        null,
        null
      ]
    },
    {
      "py/reduce": [
        {
          "py/function": "torch._utils._rebuild_tensor_v2"
        },
        {
          "py/tuple": [
            {
              "py/reduce": [
                {
                  "py/function": "torch.storage._load_from_bytes"
                },
                {
                  "py/tuple": [
                    {
                      "py/b64": "gAKKCmz8nEb5IGqoUBkugAJN6QMugAJ9cQAoWBAAAABwcm90b2NvbF92ZXJzaW9ucQFN6QNYDQAA\nAGxpdHRsZV9lbmRpYW5xAohYCgAAAHR5cGVfc2l6ZXNxA31xBChYBQAAAHNob3J0cQVLAlgDAAAA\naW50cQZLBFgEAAAAbG9uZ3EHSwR1dS6AAihYBwAAAHN0b3JhZ2VxAGN0b3JjaApGbG9hdFN0b3Jh\nZ2UKcQFYDgAAADk0NjAyMTAyODQ4ODk2cQJYBgAAAGN1ZGE6MHEDSwFOdHEEUS6AAl1xAFgOAAAA\nOTQ2MDIxMDI4NDg4OTZxAWEuAQAAAAAAAADvoF9C\n"
                    }
                  ]
                },
                null,
                null,
                null
              ]
            },
            0,
            {
              "py/tuple": []
            },
            {
              "py/tuple": []
            },
            false,
            {
              "py/reduce": [
                {
                  "py/type": "collections.OrderedDict"
                },
                {
                  "py/tuple": []
                },
                null,
                null,
                {
                  "py/tuple": []
                }
              ]
            }
          ]
        },
        null,
        null,
        null
      ]
    },
    {
      "py/reduce": [
        {
          "py/function": "torch._utils._rebuild_tensor_v2"
        },
        {
          "py/tuple": [
            {
              "py/reduce": [
                {
                  "py/function": "torch.storage._load_from_bytes"
                },
                {
                  "py/tuple": [
                    {
                      "py/b64": "gAKKCmz8nEb5IGqoUBkugAJN6QMugAJ9cQAoWBAAAABwcm90b2NvbF92ZXJzaW9ucQFN6QNYDQAA\nAGxpdHRsZV9lbmRpYW5xAohYCgAAAHR5cGVfc2l6ZXNxA31xBChYBQAAAHNob3J0cQVLAlgDAAAA\naW50cQZLBFgEAAAAbG9uZ3EHSwR1dS6AAihYBwAAAHN0b3JhZ2VxAGN0b3JjaApGbG9hdFN0b3Jh\nZ2UKcQFYDgAAADk0NjAyMTAyODEwMDAwcQJYBgAAAGN1ZGE6MHEDSwFOdHEEUS6AAl1xAFgOAAAA\nOTQ2MDIxMDI4MTAwMDBxAWEuAQAAAAAAAAA2VlFC\n"
                    }
                  ]
                },
                null,
                null,
                null
              ]
            },
            0,
            {
              "py/tuple": []
            },
            {
              "py/tuple": []
            },
            false,
            {
              "py/reduce": [
                {
                  "py/type": "collections.OrderedDict"
                },
                {
                  "py/tuple": []
                },
                null,
                null,
                {
                  "py/tuple": []
                }
              ]
            }
          ]
        },
        null,
        null,
        null
      ]
    },
    {
      "py/reduce": [
        {
          "py/function": "torch._utils._rebuild_tensor_v2"
        },
        {
          "py/tuple": [
            {
              "py/reduce": [
                {
                  "py/function": "torch.storage._load_from_bytes"
                },
                {
                  "py/tuple": [
                    {
                      "py/b64": "gAKKCmz8nEb5IGqoUBkugAJN6QMugAJ9cQAoWBAAAABwcm90b2NvbF92ZXJzaW9ucQFN6QNYDQAA\nAGxpdHRsZV9lbmRpYW5xAohYCgAAAHR5cGVfc2l6ZXNxA31xBChYBQAAAHNob3J0cQVLAlgDAAAA\naW50cQZLBFgEAAAAbG9uZ3EHSwR1dS6AAihYBwAAAHN0b3JhZ2VxAGN0b3JjaApGbG9hdFN0b3Jh\nZ2UKcQFYDgAAADk0NjA1MDAzMzc1NTg0cQJYBgAAAGN1ZGE6MHEDSwFOdHEEUS6AAl1xAFgOAAAA\nOTQ2MDUwMDMzNzU1ODRxAWEuAQAAAAAAAABPoxVB\n"
                    }
                  ]
                },
                null,
                null,
                null
              ]
            },
            0,
            {
              "py/tuple": []
            },
            {
              "py/tuple": []
            },
            false,
            {
              "py/reduce": [
                {
                  "py/type": "collections.OrderedDict"
                },
                {
                  "py/tuple": []
                },
                null,
                null,
                {
                  "py/tuple": []
                }
              ]
            }
          ]
        },
        null,
        null,
        null
      ]
    },
    {
      "py/reduce": [
        {
          "py/function": "torch._utils._rebuild_tensor_v2"
        },
        {
          "py/tuple": [
            {
              "py/reduce": [
                {
                  "py/function": "torch.storage._load_from_bytes"
                },
                {
                  "py/tuple": [
                    {
                      "py/b64": "gAKKCmz8nEb5IGqoUBkugAJN6QMugAJ9cQAoWBAAAABwcm90b2NvbF92ZXJzaW9ucQFN6QNYDQAA\nAGxpdHRsZV9lbmRpYW5xAohYCgAAAHR5cGVfc2l6ZXNxA31xBChYBQAAAHNob3J0cQVLAlgDAAAA\naW50cQZLBFgEAAAAbG9uZ3EHSwR1dS6AAihYBwAAAHN0b3JhZ2VxAGN0b3JjaApGbG9hdFN0b3Jh\nZ2UKcQFYDgAAADk0NjAyMTAyODM1NTIwcQJYBgAAAGN1ZGE6MHEDSwFOdHEEUS6AAl1xAFgOAAAA\nOTQ2MDIxMDI4MzU1MjBxAWEuAQAAAAAAAACfK+BB\n"
                    }
                  ]
                },
                null,
                null,
                null
              ]
            },
            0,
            {
              "py/tuple": []
            },
            {
              "py/tuple": []
            },
            false,
            {
              "py/reduce": [
                {
                  "py/type": "collections.OrderedDict"
                },
                {
                  "py/tuple": []
                },
                null,
                null,
                {
                  "py/tuple": []
                }
              ]
            }
          ]
        },
        null,
        null,
        null
      ]
    },
    {
      "py/reduce": [
        {
          "py/function": "torch._utils._rebuild_tensor_v2"
        },
        {
          "py/tuple": [
            {
              "py/reduce": [
                {
                  "py/function": "torch.storage._load_from_bytes"
                },
                {
                  "py/tuple": [
                    {
                      "py/b64": "gAKKCmz8nEb5IGqoUBkugAJN6QMugAJ9cQAoWBAAAABwcm90b2NvbF92ZXJzaW9ucQFN6QNYDQAA\nAGxpdHRsZV9lbmRpYW5xAohYCgAAAHR5cGVfc2l6ZXNxA31xBChYBQAAAHNob3J0cQVLAlgDAAAA\naW50cQZLBFgEAAAAbG9uZ3EHSwR1dS6AAihYBwAAAHN0b3JhZ2VxAGN0b3JjaApGbG9hdFN0b3Jh\nZ2UKcQFYDgAAADk0NjA1MDA0MDI0NDgwcQJYBgAAAGN1ZGE6MHEDSwFOdHEEUS6AAl1xAFgOAAAA\nOTQ2MDUwMDQwMjQ0ODBxAWEuAQAAAAAAAADLNcRB\n"
                    }
                  ]
                },
                null,
                null,
                null
              ]
            },
            0,
            {
              "py/tuple": []
            },
            {
              "py/tuple": []
            },
            false,
            {
              "py/reduce": [
                {
                  "py/type": "collections.OrderedDict"
                },
                {
                  "py/tuple": []
                },
                null,
                null,
                {
                  "py/tuple": []
                }
              ]
            }
          ]
        },
        null,
        null,
        null
      ]
    },
    {
      "py/reduce": [
        {
          "py/function": "torch._utils._rebuild_tensor_v2"
        },
        {
          "py/tuple": [
            {
              "py/reduce": [
                {
                  "py/function": "torch.storage._load_from_bytes"
                },
                {
                  "py/tuple": [
                    {
                      "py/b64": "gAKKCmz8nEb5IGqoUBkugAJN6QMugAJ9cQAoWBAAAABwcm90b2NvbF92ZXJzaW9ucQFN6QNYDQAA\nAGxpdHRsZV9lbmRpYW5xAohYCgAAAHR5cGVfc2l6ZXNxA31xBChYBQAAAHNob3J0cQVLAlgDAAAA\naW50cQZLBFgEAAAAbG9uZ3EHSwR1dS6AAihYBwAAAHN0b3JhZ2VxAGN0b3JjaApGbG9hdFN0b3Jh\nZ2UKcQFYDgAAADk0NjA1MDA0MDAxODQwcQJYBgAAAGN1ZGE6MHEDSwFOdHEEUS6AAl1xAFgOAAAA\nOTQ2MDUwMDQwMDE4NDBxAWEuAQAAAAAAAADzVAFC\n"
                    }
                  ]
                },
                null,
                null,
                null
              ]
            },
            0,
            {
              "py/tuple": []
            },
            {
              "py/tuple": []
            },
            false,
            {
              "py/reduce": [
                {
                  "py/type": "collections.OrderedDict"
                },
                {
                  "py/tuple": []
                },
                null,
                null,
                {
                  "py/tuple": []
                }
              ]
            }
          ]
        },
        null,
        null,
        null
      ]
    },
    {
      "py/reduce": [
        {
          "py/function": "torch._utils._rebuild_tensor_v2"
        },
        {
          "py/tuple": [
            {
              "py/reduce": [
                {
                  "py/function": "torch.storage._load_from_bytes"
                },
                {
                  "py/tuple": [
                    {
                      "py/b64": "gAKKCmz8nEb5IGqoUBkugAJN6QMugAJ9cQAoWBAAAABwcm90b2NvbF92ZXJzaW9ucQFN6QNYDQAA\nAGxpdHRsZV9lbmRpYW5xAohYCgAAAHR5cGVfc2l6ZXNxA31xBChYBQAAAHNob3J0cQVLAlgDAAAA\naW50cQZLBFgEAAAAbG9uZ3EHSwR1dS6AAihYBwAAAHN0b3JhZ2VxAGN0b3JjaApGbG9hdFN0b3Jh\nZ2UKcQFYDgAAADk0NjAyMTAyOTMwNDMycQJYBgAAAGN1ZGE6MHEDSwFOdHEEUS6AAl1xAFgOAAAA\nOTQ2MDIxMDI5MzA0MzJxAWEuAQAAAAAAAACV+xFC\n"
                    }
                  ]
                },
                null,
                null,
                null
              ]
            },
            0,
            {
              "py/tuple": []
            },
            {
              "py/tuple": []
            },
            false,
            {
              "py/reduce": [
                {
                  "py/type": "collections.OrderedDict"
                },
                {
                  "py/tuple": []
                },
                null,
                null,
                {
                  "py/tuple": []
                }
              ]
            }
          ]
        },
        null,
        null,
        null
      ]
    },
    {
      "py/reduce": [
        {
          "py/function": "torch._utils._rebuild_tensor_v2"
        },
        {
          "py/tuple": [
            {
              "py/reduce": [
                {
                  "py/function": "torch.storage._load_from_bytes"
                },
                {
                  "py/tuple": [
                    {
                      "py/b64": "gAKKCmz8nEb5IGqoUBkugAJN6QMugAJ9cQAoWBAAAABwcm90b2NvbF92ZXJzaW9ucQFN6QNYDQAA\nAGxpdHRsZV9lbmRpYW5xAohYCgAAAHR5cGVfc2l6ZXNxA31xBChYBQAAAHNob3J0cQVLAlgDAAAA\naW50cQZLBFgEAAAAbG9uZ3EHSwR1dS6AAihYBwAAAHN0b3JhZ2VxAGN0b3JjaApGbG9hdFN0b3Jh\nZ2UKcQFYDgAAADk0NjA1MDAzNDQ1NjMycQJYBgAAAGN1ZGE6MHEDSwFOdHEEUS6AAl1xAFgOAAAA\nOTQ2MDUwMDM0NDU2MzJxAWEuAQAAAAAAAAC9wBxC\n"
                    }
                  ]
                },
                null,
                null,
                null
              ]
            },
            0,
            {
              "py/tuple": []
            },
            {
              "py/tuple": []
            },
            false,
            {
              "py/reduce": [
                {
                  "py/type": "collections.OrderedDict"
                },
                {
                  "py/tuple": []
                },
                null,
                null,
                {
                  "py/tuple": []
                }
              ]
            }
          ]
        },
        null,
        null,
        null
      ]
    },
    {
      "py/reduce": [
        {
          "py/function": "torch._utils._rebuild_tensor_v2"
        },
        {
          "py/tuple": [
            {
              "py/reduce": [
                {
                  "py/function": "torch.storage._load_from_bytes"
                },
                {
                  "py/tuple": [
                    {
                      "py/b64": "gAKKCmz8nEb5IGqoUBkugAJN6QMugAJ9cQAoWBAAAABwcm90b2NvbF92ZXJzaW9ucQFN6QNYDQAA\nAGxpdHRsZV9lbmRpYW5xAohYCgAAAHR5cGVfc2l6ZXNxA31xBChYBQAAAHNob3J0cQVLAlgDAAAA\naW50cQZLBFgEAAAAbG9uZ3EHSwR1dS6AAihYBwAAAHN0b3JhZ2VxAGN0b3JjaApGbG9hdFN0b3Jh\nZ2UKcQFYDgAAADk0NjA1MDAzNDY3MjQ4cQJYBgAAAGN1ZGE6MHEDSwFOdHEEUS6AAl1xAFgOAAAA\nOTQ2MDUwMDM0NjcyNDhxAWEuAQAAAAAAAACXVjpC\n"
                    }
                  ]
                },
                null,
                null,
                null
              ]
            },
            0,
            {
              "py/tuple": []
            },
            {
              "py/tuple": []
            },
            false,
            {
              "py/reduce": [
                {
                  "py/type": "collections.OrderedDict"
                },
                {
                  "py/tuple": []
                },
                null,
                null,
                {
                  "py/tuple": []
                }
              ]
            }
          ]
        },
        null,
        null,
        null
      ]
    },
    {
      "py/reduce": [
        {
          "py/function": "torch._utils._rebuild_tensor_v2"
        },
        {
          "py/tuple": [
            {
              "py/reduce": [
                {
                  "py/function": "torch.storage._load_from_bytes"
                },
                {
                  "py/tuple": [
                    {
                      "py/b64": "gAKKCmz8nEb5IGqoUBkugAJN6QMugAJ9cQAoWBAAAABwcm90b2NvbF92ZXJzaW9ucQFN6QNYDQAA\nAGxpdHRsZV9lbmRpYW5xAohYCgAAAHR5cGVfc2l6ZXNxA31xBChYBQAAAHNob3J0cQVLAlgDAAAA\naW50cQZLBFgEAAAAbG9uZ3EHSwR1dS6AAihYBwAAAHN0b3JhZ2VxAGN0b3JjaApGbG9hdFN0b3Jh\nZ2UKcQFYDgAAADk0NjAyMTAzMjU5NDQwcQJYBgAAAGN1ZGE6MHEDSwFOdHEEUS6AAl1xAFgOAAAA\nOTQ2MDIxMDMyNTk0NDBxAWEuAQAAAAAAAADnYUtC\n"
                    }
                  ]
                },
                null,
                null,
                null
              ]
            },
            0,
            {
              "py/tuple": []
            },
            {
              "py/tuple": []
            },
            false,
            {
              "py/reduce": [
                {
                  "py/type": "collections.OrderedDict"
                },
                {
                  "py/tuple": []
                },
                null,
                null,
                {
                  "py/tuple": []
                }
              ]
            }
          ]
        },
        null,
        null,
        null
      ]
    },
    {
      "py/reduce": [
        {
          "py/function": "torch._utils._rebuild_tensor_v2"
        },
        {
          "py/tuple": [
            {
              "py/reduce": [
                {
                  "py/function": "torch.storage._load_from_bytes"
                },
                {
                  "py/tuple": [
                    {
                      "py/b64": "gAKKCmz8nEb5IGqoUBkugAJN6QMugAJ9cQAoWBAAAABwcm90b2NvbF92ZXJzaW9ucQFN6QNYDQAA\nAGxpdHRsZV9lbmRpYW5xAohYCgAAAHR5cGVfc2l6ZXNxA31xBChYBQAAAHNob3J0cQVLAlgDAAAA\naW50cQZLBFgEAAAAbG9uZ3EHSwR1dS6AAihYBwAAAHN0b3JhZ2VxAGN0b3JjaApGbG9hdFN0b3Jh\nZ2UKcQFYDgAAADk0NjAyMTAzMDE3NjAwcQJYBgAAAGN1ZGE6MHEDSwFOdHEEUS6AAl1xAFgOAAAA\nOTQ2MDIxMDMwMTc2MDBxAWEuAQAAAAAAAADFmYRC\n"
                    }
                  ]
                },
                null,
                null,
                null
              ]
            },
            0,
            {
              "py/tuple": []
            },
            {
              "py/tuple": []
            },
            false,
            {
              "py/reduce": [
                {
                  "py/type": "collections.OrderedDict"
                },
                {
                  "py/tuple": []
                },
                null,
                null,
                {
                  "py/tuple": []
                }
              ]
            }
          ]
        },
        null,
        null,
        null
      ]
    },
    {
      "py/reduce": [
        {
          "py/function": "torch._utils._rebuild_tensor_v2"
        },
        {
          "py/tuple": [
            {
              "py/reduce": [
                {
                  "py/function": "torch.storage._load_from_bytes"
                },
                {
                  "py/tuple": [
                    {
                      "py/b64": "gAKKCmz8nEb5IGqoUBkugAJN6QMugAJ9cQAoWBAAAABwcm90b2NvbF92ZXJzaW9ucQFN6QNYDQAA\nAGxpdHRsZV9lbmRpYW5xAohYCgAAAHR5cGVfc2l6ZXNxA31xBChYBQAAAHNob3J0cQVLAlgDAAAA\naW50cQZLBFgEAAAAbG9uZ3EHSwR1dS6AAihYBwAAAHN0b3JhZ2VxAGN0b3JjaApGbG9hdFN0b3Jh\nZ2UKcQFYDgAAADk0NjA1MDAzMzkxNTY4cQJYBgAAAGN1ZGE6MHEDSwFOdHEEUS6AAl1xAFgOAAAA\nOTQ2MDUwMDMzOTE1NjhxAWEuAQAAAAAAAADEAc5C\n"
                    }
                  ]
                },
                null,
                null,
                null
              ]
            },
            0,
            {
              "py/tuple": []
            },
            {
              "py/tuple": []
            },
            false,
            {
              "py/reduce": [
                {
                  "py/type": "collections.OrderedDict"
                },
                {
                  "py/tuple": []
                },
                null,
                null,
                {
                  "py/tuple": []
                }
              ]
            }
          ]
        },
        null,
        null,
        null
      ]
    },
    {
      "py/reduce": [
        {
          "py/function": "torch._utils._rebuild_tensor_v2"
        },
        {
          "py/tuple": [
            {
              "py/reduce": [
                {
                  "py/function": "torch.storage._load_from_bytes"
                },
                {
                  "py/tuple": [
                    {
                      "py/b64": "gAKKCmz8nEb5IGqoUBkugAJN6QMugAJ9cQAoWBAAAABwcm90b2NvbF92ZXJzaW9ucQFN6QNYDQAA\nAGxpdHRsZV9lbmRpYW5xAohYCgAAAHR5cGVfc2l6ZXNxA31xBChYBQAAAHNob3J0cQVLAlgDAAAA\naW50cQZLBFgEAAAAbG9uZ3EHSwR1dS6AAihYBwAAAHN0b3JhZ2VxAGN0b3JjaApGbG9hdFN0b3Jh\nZ2UKcQFYDgAAADk0NjAyMTAyODg3OTM2cQJYBgAAAGN1ZGE6MHEDSwFOdHEEUS6AAl1xAFgOAAAA\nOTQ2MDIxMDI4ODc5MzZxAWEuAQAAAAAAAABfqxpC\n"
                    }
                  ]
                },
                null,
                null,
                null
              ]
            },
            0,
            {
              "py/tuple": []
            },
            {
              "py/tuple": []
            },
            false,
            {
              "py/reduce": [
                {
                  "py/type": "collections.OrderedDict"
                },
                {
                  "py/tuple": []
                },
                null,
                null,
                {
                  "py/tuple": []
                }
              ]
            }
          ]
        },
        null,
        null,
        null
      ]
    },
    {
      "py/reduce": [
        {
          "py/function": "torch._utils._rebuild_tensor_v2"
        },
        {
          "py/tuple": [
            {
              "py/reduce": [
                {
                  "py/function": "torch.storage._load_from_bytes"
                },
                {
                  "py/tuple": [
                    {
                      "py/b64": "gAKKCmz8nEb5IGqoUBkugAJN6QMugAJ9cQAoWBAAAABwcm90b2NvbF92ZXJzaW9ucQFN6QNYDQAA\nAGxpdHRsZV9lbmRpYW5xAohYCgAAAHR5cGVfc2l6ZXNxA31xBChYBQAAAHNob3J0cQVLAlgDAAAA\naW50cQZLBFgEAAAAbG9uZ3EHSwR1dS6AAihYBwAAAHN0b3JhZ2VxAGN0b3JjaApGbG9hdFN0b3Jh\nZ2UKcQFYDgAAADk0NjAyMTAzNDI2MDgwcQJYBgAAAGN1ZGE6MHEDSwFOdHEEUS6AAl1xAFgOAAAA\nOTQ2MDIxMDM0MjYwODBxAWEuAQAAAAAAAADnZi5C\n"
                    }
                  ]
                },
                null,
                null,
                null
              ]
            },
            0,
            {
              "py/tuple": []
            },
            {
              "py/tuple": []
            },
            false,
            {
              "py/reduce": [
                {
                  "py/type": "collections.OrderedDict"
                },
                {
                  "py/tuple": []
                },
                null,
                null,
                {
                  "py/tuple": []
                }
              ]
            }
          ]
        },
        null,
        null,
        null
      ]
    },
    {
      "py/reduce": [
        {
          "py/function": "torch._utils._rebuild_tensor_v2"
        },
        {
          "py/tuple": [
            {
              "py/reduce": [
                {
                  "py/function": "torch.storage._load_from_bytes"
                },
                {
                  "py/tuple": [
                    {
                      "py/b64": "gAKKCmz8nEb5IGqoUBkugAJN6QMugAJ9cQAoWBAAAABwcm90b2NvbF92ZXJzaW9ucQFN6QNYDQAA\nAGxpdHRsZV9lbmRpYW5xAohYCgAAAHR5cGVfc2l6ZXNxA31xBChYBQAAAHNob3J0cQVLAlgDAAAA\naW50cQZLBFgEAAAAbG9uZ3EHSwR1dS6AAihYBwAAAHN0b3JhZ2VxAGN0b3JjaApGbG9hdFN0b3Jh\nZ2UKcQFYDgAAADk0NjA1MDAzMzgzODU2cQJYBgAAAGN1ZGE6MHEDSwFOdHEEUS6AAl1xAFgOAAAA\nOTQ2MDUwMDMzODM4NTZxAWEuAQAAAAAAAAD32r5B\n"
                    }
                  ]
                },
                null,
                null,
                null
              ]
            },
            0,
            {
              "py/tuple": []
            },
            {
              "py/tuple": []
            },
            false,
            {
              "py/reduce": [
                {
                  "py/type": "collections.OrderedDict"
                },
                {
                  "py/tuple": []
                },
                null,
                null,
                {
                  "py/tuple": []
                }
              ]
            }
          ]
        },
        null,
        null,
        null
      ]
    },
    {
      "py/reduce": [
        {
          "py/function": "torch._utils._rebuild_tensor_v2"
        },
        {
          "py/tuple": [
            {
              "py/reduce": [
                {
                  "py/function": "torch.storage._load_from_bytes"
                },
                {
                  "py/tuple": [
                    {
                      "py/b64": "gAKKCmz8nEb5IGqoUBkugAJN6QMugAJ9cQAoWBAAAABwcm90b2NvbF92ZXJzaW9ucQFN6QNYDQAA\nAGxpdHRsZV9lbmRpYW5xAohYCgAAAHR5cGVfc2l6ZXNxA31xBChYBQAAAHNob3J0cQVLAlgDAAAA\naW50cQZLBFgEAAAAbG9uZ3EHSwR1dS6AAihYBwAAAHN0b3JhZ2VxAGN0b3JjaApGbG9hdFN0b3Jh\nZ2UKcQFYDgAAADk0NjAyMTAyOTY5OTUycQJYBgAAAGN1ZGE6MHEDSwFOdHEEUS6AAl1xAFgOAAAA\nOTQ2MDIxMDI5Njk5NTJxAWEuAQAAAAAAAADX8qBC\n"
                    }
                  ]
                },
                null,
                null,
                null
              ]
            },
            0,
            {
              "py/tuple": []
            },
            {
              "py/tuple": []
            },
            false,
            {
              "py/reduce": [
                {
                  "py/type": "collections.OrderedDict"
                },
                {
                  "py/tuple": []
                },
                null,
                null,
                {
                  "py/tuple": []
                }
              ]
            }
          ]
        },
        null,
        null,
        null
      ]
    },
    {
      "py/reduce": [
        {
          "py/function": "torch._utils._rebuild_tensor_v2"
        },
        {
          "py/tuple": [
            {
              "py/reduce": [
                {
                  "py/function": "torch.storage._load_from_bytes"
                },
                {
                  "py/tuple": [
                    {
                      "py/b64": "gAKKCmz8nEb5IGqoUBkugAJN6QMugAJ9cQAoWBAAAABwcm90b2NvbF92ZXJzaW9ucQFN6QNYDQAA\nAGxpdHRsZV9lbmRpYW5xAohYCgAAAHR5cGVfc2l6ZXNxA31xBChYBQAAAHNob3J0cQVLAlgDAAAA\naW50cQZLBFgEAAAAbG9uZ3EHSwR1dS6AAihYBwAAAHN0b3JhZ2VxAGN0b3JjaApGbG9hdFN0b3Jh\nZ2UKcQFYDgAAADk0NjAyMTAzMDE4MzA0cQJYBgAAAGN1ZGE6MHEDSwFOdHEEUS6AAl1xAFgOAAAA\nOTQ2MDIxMDMwMTgzMDRxAWEuAQAAAAAAAAAnKlBC\n"
                    }
                  ]
                },
                null,
                null,
                null
              ]
            },
            0,
            {
              "py/tuple": []
            },
            {
              "py/tuple": []
            },
            false,
            {
              "py/reduce": [
                {
                  "py/type": "collections.OrderedDict"
                },
                {
                  "py/tuple": []
                },
                null,
                null,
                {
                  "py/tuple": []
                }
              ]
            }
          ]
        },
        null,
        null,
        null
      ]
    },
    {
      "py/reduce": [
        {
          "py/function": "torch._utils._rebuild_tensor_v2"
        },
        {
          "py/tuple": [
            {
              "py/reduce": [
                {
                  "py/function": "torch.storage._load_from_bytes"
                },
                {
                  "py/tuple": [
                    {
                      "py/b64": "gAKKCmz8nEb5IGqoUBkugAJN6QMugAJ9cQAoWBAAAABwcm90b2NvbF92ZXJzaW9ucQFN6QNYDQAA\nAGxpdHRsZV9lbmRpYW5xAohYCgAAAHR5cGVfc2l6ZXNxA31xBChYBQAAAHNob3J0cQVLAlgDAAAA\naW50cQZLBFgEAAAAbG9uZ3EHSwR1dS6AAihYBwAAAHN0b3JhZ2VxAGN0b3JjaApGbG9hdFN0b3Jh\nZ2UKcQFYDgAAADk0NjA1MDA0MDAwNDgwcQJYBgAAAGN1ZGE6MHEDSwFOdHEEUS6AAl1xAFgOAAAA\nOTQ2MDUwMDQwMDA0ODBxAWEuAQAAAAAAAAASbLJC\n"
                    }
                  ]
                },
                null,
                null,
                null
              ]
            },
            0,
            {
              "py/tuple": []
            },
            {
              "py/tuple": []
            },
            false,
            {
              "py/reduce": [
                {
                  "py/type": "collections.OrderedDict"
                },
                {
                  "py/tuple": []
                },
                null,
                null,
                {
                  "py/tuple": []
                }
              ]
            }
          ]
        },
        null,
        null,
        null
      ]
    }
  ],
  "grad_norm_T": [
    320,
    10320,
    20320,
    30320,
    40320,
    50320,
    60320,
    70320,
    80320,
    90320,
    100320,
    110320,
    120320,
    130320,
    140320,
    150320,
    160320,
    170320,
    180320,
    190320,
    200320
  ],
  "loss": [
    66.30680084228516,
    169.91514587402344,
    440.3241271972656,
    655.972900390625,
    751.29541015625,
    810.2597045898438,
    831.0232543945312,
    829.7135009765625,
    814.43017578125,
    790.4710693359375,
    784.8228149414062,
    773.6276245117188,
    771.1492309570312,
    773.2673950195312,
    765.7178955078125,
    767.090087890625,
    774.3411254882812,
    785.1394653320312,
    789.7731323242188,
    788.4368896484375,
    787.7280883789062
  ],
  "loss_T": [
    320,
    10320,
    20320,
    30320,
    40320,
    50320,
    60320,
    70320,
    80320,
    90320,
    100320,
    110320,
    120320,
    130320,
    140320,
    150320,
    160320,
    170320,
    180320,
    190320,
    200320
  ],
  "q_taken_mean": [
    0.4274274698893229,
    -3.3478995768229165,
    -5.018603922526042,
    -5.886390380859375,
    -6.288475748697917,
    -6.493667805989583,
    -6.557337646484375,
    -6.574212239583333,
    -6.496401774088541,
    -6.433882649739584,
    -6.416064046223958,
    -6.344814453125,
    -6.319922281901042,
    -6.364715983072917,
    -6.357422281901042,
    -6.329270426432291,
    -6.3318505859375,
    -6.382181803385417,
    -6.3967529296875,
    -6.405167643229166,
    -6.38806396484375
  ],
  "q_taken_mean_T": [
    320,
    10320,
    20320,
    30320,
    40320,
    50320,
    60320,
    70320,
    80320,
    90320,
    100320,
    110320,
    120320,
    130320,
    140320,
    150320,
    160320,
    170320,
    180320,
    190320,
    200320
  ],
  "return_mean": [
    -111.0,
    -117.0575,
    -114.819,
    -111.638,
    -109.085,
    -105.7945,
    -103.8465,
    -104.1895,
    -103.4445,
    -103.6535,
    -103.9885,
    -104.031,
    -103.941,
    -103.6565,
    -103.594,
    -104.042,
    -104.148,
    -103.9305,
    -104.3565,
    -104.2655,
    -104.0415
  ],
  "return_mean_T": [
    10,
    10010,
    20010,
    30010,
    40010,
    50010,
    60010,
    70010,
    80010,
    90010,
    100010,
    110010,
    120010,
    130010,
    140010,
    150010,
    160010,
    170010,
    180010,
    190010,
    200010
  ],
  "return_std": [
    0.0,
    6.133265341561541,
    6.153717494328124,
    6.2433529453331404,
    5.949813022272212,
    6.159749974633711,
    5.795876788717994,
    5.812644815400301,
    5.979520862912011,
    6.1438740018004925,
    5.721155281059937,
    5.972984095073417,
    5.9198833603374315,
    5.913734670240118,
    5.964952975506177,
    5.881984019019432,
    5.91566530493401,
    5.83630188989569,
    5.922217300133456,
    6.0445231201476926,
    5.981181133354849
  ],
  "return_std_T": [
    10,
    10010,
    20010,
    30010,
    40010,
    50010,
    60010,
    70010,
    80010,
    90010,
    100010,
    110010,
    120010,
    130010,
    140010,
    150010,
    160010,
    170010,
    180010,
    190010,
    200010
  ],
  "scaned_mean": [
    0.0,
    1.655,
    1.967,
    2.334,
    2.653,
    3.08,
    3.35,
    3.292,
    3.453,
    3.425,
    3.325,
    3.359,
    3.356,
    3.412,
    3.452,
    3.34,
    3.328,
    3.363,
    3.258,
    3.258,
    3.333
  ],
  "scaned_mean_T": [
    10,
    10010,
    20010,
    30010,
    40010,
    50010,
    60010,
    70010,
    80010,
    90010,
    100010,
    110010,
    120010,
    130010,
    140010,
    150010,
    160010,
    170010,
    180010,
    190010,
    200010
  ],
  "target_mean": [
    -0.0465182367960612,
    -3.3588433837890626,
    -5.019794108072917,
    -5.905137125651041,
    -6.306322428385417,
    -6.493656005859375,
    -6.548828531901042,
    -6.564109293619792,
    -6.508151041666666,
    -6.421420084635416,
    -6.404814453125,
    -6.36332763671875,
    -6.33910888671875,
    -6.3428759765625,
    -6.325489095052084,
    -6.345308837890625,
    -6.3481758626302085,
    -6.39126953125,
    -6.423409830729167,
    -6.4231966145833335,
    -6.4184423828125
  ],
  "target_mean_T": [
    320,
    10320,
    20320,
    30320,
    40320,
    50320,
    60320,
    70320,
    80320,
    90320,
    100320,
    110320,
    120320,
    130320,
    140320,
    150320,
    160320,
    170320,
    180320,
    190320,
    200320
  ],
  "td_error_abs": [
    7.109185791015625,
    7.9342597961425785,
    12.523347473144531,
    15.515594482421875,
    16.566873168945314,
    16.991546630859375,
    17.177432250976562,
    17.141802978515624,
    17.197917175292968,
    16.844261169433594,
    16.785113525390624,
    16.936422729492186,
    16.943930053710936,
    16.627117919921876,
    16.41308135986328,
    16.92046203613281,
    16.929547119140626,
    17.0700439453125,
    17.26109924316406,
    17.192611694335938,
    17.14171905517578
  ],
  "td_error_abs_T": [
    320,
    10320,
    20320,
    30320,
    40320,
    50320,
    60320,
    70320,
    80320,
    90320,
    100320,
    110320,
    120320,
    130320,
    140320,
    150320,
    160320,
    170320,
    180320,
    190320,
    200320
  ],
  "test_battle_won_mean": [
    0.0,
    0.0,
    0.0,
    0.0,
    0.0,
    0.0,
    0.0,
    0.0,
    0.0,
    0.0,
    0.0,
    0.0,
    0.0,
    0.0,
    0.0,
    0.0,
    0.0,
    0.0,
    0.0,
    0.0,
    0.0
  ],
  "test_battle_won_mean_T": [
    10,
    10010,
    20010,
    30010,
    40010,
    50010,
    60010,
    70010,
    80010,
    90010,
    100010,
    110010,
    120010,
    130010,
    140010,
    150010,
    160010,
    170010,
    180010,
    190010,
    200010
  ],
  "test_ep_length_mean": [
    10.0,
    10.0,
    10.0,
    10.0,
    10.0,
    10.0,
    10.0,
    10.0,
    10.0,
    10.0,
    10.0,
    10.0,
    10.0,
    10.0,
    10.0,
    10.0,
    10.0,
    10.0,
    10.0,
    10.0,
    10.0
  ],
  "test_ep_length_mean_T": [
    10,
    10010,
    20010,
    30010,
    40010,
    50010,
    60010,
    70010,
    80010,
    90010,
    100010,
    110010,
    120010,
    130010,
    140010,
    150010,
    160010,
    170010,
    180010,
    190010,
    200010
  ],
  "test_return_mean": [
    -138.50333333333333,
    -99.56,
    -101.50833333333334,
    -103.06666666666666,
    -102.885,
    -103.37333333333333,
    -103.02833333333334,
    -102.44833333333334,
    -102.73333333333333,
    -103.56833333333333,
    -102.775,
    -103.22833333333334,
    -102.85333333333334,
    -103.41666666666667,
    -103.01,
    -102.78833333333333,
    -103.20333333333333,
    -102.71833333333333,
    -103.385,
    -102.85166666666667,
    -102.58666666666667
  ],
  "test_return_mean_T": [
    10,
    10010,
    20010,
    30010,
    40010,
    50010,
    60010,
    70010,
    80010,
    90010,
    100010,
    110010,
    120010,
    130010,
    140010,
    150010,
    160010,
    170010,
    180010,
    190010,
    200010
  ],
  "test_return_std": [
    1.6401185594001702,
    6.429339001794819,
    6.401882318679578,
    5.752004481531248,
    5.791454192745261,
    6.007685818090764,
    6.002224356205142,
    5.807451869987578,
    5.945773475522105,
    6.185560919503492,
    5.599423333403777,
    5.632823201754358,
    6.036015978183696,
    5.413537557724052,
    5.815344644415612,
    6.017006223105382,
    5.831265347723043,
    6.2097904330357405,
    5.598298104483779,
    5.601234734909398,
    5.753476243879772
  ],
  "test_return_std_T": [
    10,
    10010,
    20010,
    30010,
    40010,
    50010,
    60010,
    70010,
    80010,
    90010,
    100010,
    110010,
    120010,
    130010,
    140010,
    150010,
    160010,
    170010,
    180010,
    190010,
    200010
  ],
  "test_scaned_mean": [
    0.18666666666666668,
    3.7866666666666666,
    3.4466666666666668,
    3.433333333333333,
    3.486666666666667,
    3.3933333333333335,
    3.5,
    3.6066666666666665,
    3.546666666666667,
    3.32,
    3.546666666666667,
    3.3566666666666665,
    3.4833333333333334,
    3.3466666666666667,
    3.4366666666666665,
    3.5366666666666666,
    3.4166666666666665,
    3.5366666666666666,
    3.4,
    3.5,
    3.5633333333333335
  ],
  "test_scaned_mean_T": [
    10,
    10010,
    20010,
    30010,
    40010,
    50010,
    60010,
    70010,
    80010,
    90010,
    100010,
    110010,
    120010,
    130010,
    140010,
    150010,
    160010,
    170010,
    180010,
    190010,
    200010
  ]
}